socat2pcap/pcap.py
socat2pcap/__main__.py
socat2pcap/main.py
socat2pcap/__init__.py
socat2pcap/socat.py
socat2pcap/common.py
socat2pcap-0.1.0.dist-info/LICENSE
socat2pcap-0.1.0.dist-info/entry_points.txt
socat2pcap-0.1.0.dist-info/METADATA
socat2pcap-0.1.0.dist-info/WHEEL
socat2pcap-0.1.0.dist-info/RECORD
