Metadata-Version: 2.1
Name: socat2pcap
Version: 0.1.0
Summary: Socat log to pcap converter
Author: Bozo Kopic
Author-email: "Bozo Kopic" <bozo@kopic.xyz>
License: GPLv3
Classifier: Programming Language :: Python :: 3
Classifier: License :: OSI Approved :: GNU General Public License v3 (GPLv3)
Requires-Python: >=3.10
Project-URL: Repository, https://github.com/bozokopic/socat2pcap.git
